MEMORY/FIFO/sys_fifo.v
module sys_fifo(
input clk,rst,re,we,
input [7:0] data_in,
output full,
output empty,
output reg [7:0] data_out);

reg [7:0]mem[7:0];
reg [3:0] wr_ptr=4'b0000;
reg [3:0] rd_ptr=4'b0000;

integer i;
always @(posedge clk)
begin
if(rst) begin
for(i=0;i<8;i=i+1)
mem[i]<=0;
wr_ptr <= 4'b0000;
end
else if(we && !full) begin
mem[wr_ptr[2:0]]<=data_in;   // Write Operation
wr_ptr<=wr_ptr+1;
end
end

always @(posedge clk) begin
if(rst) begin
data_out<=0;
rd_ptr <= 4'b0000;
end
else if(re && !empty ) begin
data_out<=mem[rd_ptr[2:0]];
rd_ptr<=rd_ptr+1;
end
end

assign full=(wr_ptr[3]!=rd_ptr[3] && wr_ptr[2:0]==rd_ptr[2:0]) ? 1:0;
assign empty=(wr_ptr==rd_ptr) ? 1:0;
endmodule

MEMORY/FIFO/sys_fifo_tb.v
`timescale 1ns/1ps

module sys_fifo_tb;

reg clk;
reg rst;
reg we;
reg re;
reg [7:0] data_in;

wire full;
wire empty;
wire [7:0] data_out;

sys_fifo dut (
    .clk(clk),
    .rst(rst),
    .we(we),
    .re(re),
    .data_in(data_in),
    .full(full),
    .empty(empty),
    .data_out(data_out)
);

// Clock: 50 MHz
initial begin
    clk = 0;
    forever #10 clk = ~clk;
end

initial begin

    $dumpfile("sys_fifo.vcd");
    $dumpvars(0, sys_fifo_tb);

    // Initial values
    rst     = 1;
    we      = 0;
    re      = 0;
    data_in = 8'h00;

    // -------------------------
    // CASE 1: RESET
    // -------------------------
    #20;
    rst = 0;

    #10;
    $display("CASE 1: RESET");
    $display("empty=%b full=%b", empty, full);


    // -------------------------
    // CASE 2: WRITE 8 VALUES
    // -------------------------
    we = 1;

    data_in = 8'hA5;
    #20;
    $display("WRITE: A5 | empty=%b full=%b", empty, full);

    data_in = 8'h3C;
    #20;
    $display("WRITE: 3C | empty=%b full=%b", empty, full);

    data_in = 8'h11;
    #20;
    $display("WRITE: 11 | empty=%b full=%b", empty, full);

    data_in = 8'h22;
    #20;
    $display("WRITE: 22 | empty=%b full=%b", empty, full);

    data_in = 8'h33;
    #20;
    $display("WRITE: 33 | empty=%b full=%b", empty, full);

    data_in = 8'h44;
    #20;
    $display("WRITE: 44 | empty=%b full=%b", empty, full);

    data_in = 8'h55;
    #20;
    $display("WRITE: 55 | empty=%b full=%b", empty, full);

    data_in = 8'h66;
    #20;
    $display("WRITE: 66 | empty=%b full=%b", empty, full);

    we = 0;

    #10;
    $display("CASE 2: AFTER 8 WRITES");
    $display("empty=%b full=%b", empty, full);


    // -------------------------
    // CASE 3: TRY WRITE WHEN FULL
    // -------------------------
    we = 1;
    data_in = 8'hFF;

    #20;

    we = 0;

    $display("CASE 3: WRITE WHEN FULL");
    $display("Tried to write FF");
    $display("empty=%b full=%b", empty, full);


    // -------------------------
    // CASE 4: READ ALL 8 VALUES
    // -------------------------
    re = 1;

    #20;
    $display("READ 1: data_out=%h | empty=%b full=%b",
             data_out, empty, full);

    #20;
    $display("READ 2: data_out=%h | empty=%b full=%b",
             data_out, empty, full);

    #20;
    $display("READ 3: data_out=%h | empty=%b full=%b",
             data_out, empty, full);

    #20;
    $display("READ 4: data_out=%h | empty=%b full=%b",
             data_out, empty, full);

    #20;
    $display("READ 5: data_out=%h | empty=%b full=%b",
             data_out, empty, full);

    #20;
    $display("READ 6: data_out=%h | empty=%b full=%b",
             data_out, empty, full);

    #20;
    $display("READ 7: data_out=%h | empty=%b full=%b",
             data_out, empty, full);

    #20;
    $display("READ 8: data_out=%h | empty=%b full=%b",
             data_out, empty, full);

    re = 0;


    // -------------------------
    // CASE 5: FIFO EMPTY
    // -------------------------
    #10;

    $display("CASE 5: AFTER 8 READS");
    $display("empty=%b full=%b", empty, full);


    // -------------------------
    // CASE 6: TRY READ WHEN EMPTY
    // -------------------------
    re = 1;

    #20;

    re = 0;

    $display("CASE 6: READ WHEN EMPTY");
    $display("data_out=%h | empty=%b full=%b",
             data_out, empty, full);


    // -------------------------
    // END
    // -------------------------
    #20;

    $display("================================");
    $display("FIFO TEST COMPLETED");
    $display("================================");

    $finish;

end

endmodule

MEMORY/FIFO/sys_fifo.vcd
$date
	Wed Sep  2 07:36:57 2026
$end
$version
	Icarus Verilog
$end
$timescale
	1ps
$end
$scope module sys_fifo_tb $end
$var wire 1 ! full $end
$var wire 1 " empty $end
$var wire 8 # data_out [7:0] $end
$var reg 1 $ clk $end
$var reg 8 % data_in [7:0] $end
$var reg 1 & re $end
$var reg 1 ' rst $end
$var reg 1 ( we $end
$scope module dut $end
$var wire 1 $ clk $end
$var wire 8 ) data_in [7:0] $end
$var wire 1 & re $end
$var wire 1 ' rst $end
$var wire 1 ( we $end
$var wire 1 ! full $end
$var wire 1 " empty $end
$var reg 8 * data_out [7:0] $end
$var reg 4 + rd_ptr [3:0] $end
$var reg 4 , wr_ptr [3:0] $end
$var integer 32 - i [31:0] $end
$upscope $end
$upscope $end
$enddefinitions $end
$comment Show the parameter values. $end
$dumpall
$end
#0
$dumpvars
bx -
b0 ,
b0 +
bx *
b0 )
0(
1'
0&
b0 %
0$
bx #
1"
0!
$end
#10000
b0 #
b0 *
b1000 -
1$
#20000
0$
0'
#30000
0"
b1 ,
1$
b10100101 %
b10100101 )
1(
#40000
0$
#50000
b10 ,
1$
b111100 %
b111100 )
#60000
0$
#70000
b11 ,
1$
b10001 %
b10001 )
#80000
0$
#90000
b100 ,
1$
b100010 %
b100010 )
#100000
0$
#110000
b101 ,
1$
b110011 %
b110011 )
#120000
0$
#130000
b110 ,
1$
b1000100 %
b1000100 )
#140000
0$
#150000
b111 ,
1$
b1010101 %
b1010101 )
#160000
0$
#170000
1!
b1000 ,
1$
b1100110 %
b1100110 )
#180000
0$
#190000
1$
0(
#200000
0$
b11111111 %
b11111111 )
1(
#210000
1$
#220000
0$
1&
0(
#230000
0!
b1 +
b10100101 #
b10100101 *
1$
#240000
0$
#250000
b10 +
b111100 #
b111100 *
1$
#260000
0$
#270000
b11 +
b10001 #
b10001 *
1$
#280000
0$
#290000
b100 +
b100010 #
b100010 *
1$
#300000
0$
#310000
b101 +
b110011 #
b110011 *
1$
#320000
0$
#330000
b110 +
b1000100 #
b1000100 *
1$
#340000
0$
#350000
b111 +
b1010101 #
b1010101 *
1$
#360000
0$
#370000
0!
1"
b1000 +
b1100110 #
b1100110 *
1$
#380000
0$
0&
#390000
1$
1&
#400000
0$
#410000
1$
0&
