MEMORY/FIFO/sys_fifo.v
module sys_fifo(
input clk,rst,re,we,
input [7:0] data_in,
output full,
output empty,
output reg [7:0] data_out);

reg [7:0]mem[7:0];
reg [2:0] wr_ptr=3'b000;
reg [2:0] rd_ptr=3'b000;

integer i;
always @(posedge clk)
begin
if(rst) begin
for(i=0;i<8;i=i+1)
mem[i]<=3'b000;
end
else if(we) begin
mem[wr_ptr]<=data_in;   // Write Operation
wr_ptr<=wr_ptr+1;
end
end

always @(posedge clk) begin
if(rst) 
data_out<=0;
else if(re) begin
data_out<=mem[rd_ptr];
rd_ptr<=rd_ptr+1;
end
end

assign full=((wr_ptr+1'b1)==rd_ptr) ? 1:0;
assign empty=(wr_ptr==rd_ptr) ? 1:0;
endmodule

MEMORY/FIFO/sys_fifo_tb.v
module sys_fifo_tb();
reg clk,rst,we,re;
reg [7:0] data_in;
wire full,empty;
wire [7:0] data_out;
integer i;
sys_fifo dut(.clk(clk),.rst(rst),.we(we),.re(re),.data_in(data_in),.full(full),.empty(empty),.data_out(data_out));
initial begin
clk=0;
forever #10 clk=~clk;
end

initial begin
$dumpfile("sys_fifo.vcd");
$dumpvars(0,sys_fifo_tb);

rst=1;we=0;re=0;data_in=0;
#20;
rst=0;#20;
$display("After Reset --> full=%b empty=%b",full,empty);

$display("\n filling FIFO");
for(i=0;i<8;i=i+1) begin
we=1;
data_in=i+8'h10;
#20;
$display("Wrote %h|full=%b|empty=%b",data_in,full,empty);
end 
we=0;
#20;

$display("Final state after fill attempts -> full=%b empty=%b", full, empty);
$display("\n--- Draining FIFO ---");
for (i = 0; i < 8; i = i + 1) begin
re = 1;
#20;
$display("Read data_out=%h | full=%b empty=%b", data_out, full, empty);
end

re = 0;
#20;
$finish;
end 
endmodule

MEMORY/FIFO/sys_fifo.vcd
$date
	Mon Aug 31 12:19:24 2026
$end
$version
	Icarus Verilog
$end
$timescale
	1s
$end
$scope module sys_fifo_tb $end
$var wire 1 ! full $end
$var wire 1 " empty $end
$var wire 8 # data_out [7:0] $end
$var reg 1 $ clk $end
$var reg 8 % data_in [7:0] $end
$var reg 1 & re $end
$var reg 1 ' rst $end
$var reg 1 ( we $end
$var integer 32 ) i [31:0] $end
$scope module dut $end
$var wire 1 $ clk $end
$var wire 8 * data_in [7:0] $end
$var wire 1 & re $end
$var wire 1 ' rst $end
$var wire 1 ( we $end
$var wire 1 ! full $end
$var wire 1 " empty $end
$var reg 8 + data_out [7:0] $end
$var reg 3 , rd_ptr [2:0] $end
$var reg 3 - wr_ptr [2:0] $end
$var integer 32 . i [31:0] $end
$upscope $end
$upscope $end
$enddefinitions $end
$comment Show the parameter values. $end
$dumpall
$end
#0
$dumpvars
bx .
b0 -
b0 ,
bx +
b0 *
bx )
0(
1'
0&
b0 %
0$
bx #
1"
0!
$end
#10
b0 #
b0 +
b1000 .
1$
#20
0$
0'
#30
1$
#40
0$
b10000 %
b10000 *
1(
b0 )
#50
0"
b1 -
1$
#60
0$
b10001 %
b10001 *
b1 )
#70
b10 -
1$
#80
0$
b10010 %
b10010 *
b10 )
#90
b11 -
1$
#100
0$
b10011 %
b10011 *
b11 )
#110
b100 -
1$
#120
0$
b10100 %
b10100 *
b100 )
#130
b101 -
1$
#140
0$
b10101 %
b10101 *
b101 )
#150
b110 -
1$
#160
0$
b10110 %
b10110 *
b110 )
#170
1!
b111 -
1$
#180
0$
b10111 %
b10111 *
b111 )
#190
0!
1"
b0 -
1$
#200
0$
0(
b1000 )
#210
1$
#220
0$
1&
b0 )
#230
1!
0"
b1 ,
b10000 #
b10000 +
1$
#240
0$
b1 )
#250
0!
b10 ,
b10001 #
b10001 +
1$
#260
0$
b10 )
#270
b11 ,
b10010 #
b10010 +
1$
#280
0$
b11 )
#290
b100 ,
b10011 #
b10011 +
1$
#300
0$
b100 )
#310
b101 ,
b10100 #
b10100 +
1$
#320
0$
b101 )
#330
b110 ,
b10101 #
b10101 +
1$
#340
0$
b110 )
#350
b111 ,
b10110 #
b10110 +
1$
#360
0$
b111 )
#370
1"
b0 ,
b10111 #
b10111 +
1$
#380
0$
0&
b1000 )
