MEMORY/RAM/dual_report.v
module dual_port(input clk,we,re,input [2:0] addr,input [7:0] data_in,output reg [7:0] data_out);
reg [7:0] mem [7:0];
always @(posedge clk) begin
if(we)
mem[addr]<=data_in;
end
always @(posedge clk) begin
if(re)
data_out<=mem[addr];
else
data_out<=0;
end
endmodule

MEMORY/RAM/dual_report_tb.v
module dual_port_tb();
    reg clk, we,re;
    reg [7:0] in;
    reg [2:0] addr;
    wire [7:0] out;

    dual_port uut (.clk(clk), .we(we),.re(re), .data_in(in), .addr(addr), .data_out(out));

    initial begin
        clk = 0;
        forever #10 clk = ~clk;
    end

    initial begin
        // Waveform dump setup
        $dumpfile("dual_port.vcd");
        $dumpvars(0, dual_port_tb);

        // write 0xA5 into address 2
        addr = 3'b010;
        in   = 8'hA5;
        we   = 1;
        #20;
	we=0;
        re = 1;
        #20;
        $display("Read from address reg 2:%h", out);
	re=0;

        // write 0x3C into address 5, then re-check address 2
        addr = 3'b101;
        in   = 8'h3C;
        we   = 1;
        #20;
        we= 0;
	re=1;
        #20;
        $display("Read from address reg 5:%h", out);
	re=0;

        addr = 3'b010;
        #20;
        $display("Read from address reg 2 again:%h", out);

        #20;
        $finish;
    end
endmodule

MEMORY/RAM/dual_port.vcd
$date
	Fri Aug 28 12:11:11 2026
$end
$version
	Icarus Verilog
$end
$timescale
	1s
$end
$scope module dual_port_tb $end
$var wire 8 ! out [7:0] $end
$var reg 3 " addr [2:0] $end
$var reg 1 # clk $end
$var reg 8 $ in [7:0] $end
$var reg 1 % re $end
$var reg 1 & we $end
$scope module uut $end
$var wire 3 ' addr [2:0] $end
$var wire 1 # clk $end
$var wire 8 ( data_in [7:0] $end
$var wire 1 % re $end
$var wire 1 & we $end
$var reg 8 ) data_out [7:0] $end
$upscope $end
$upscope $end
$enddefinitions $end
$comment Show the parameter values. $end
$dumpall
$end
#0
$dumpvars
bx )
b10100101 (
b10 '
1&
x%
b10100101 $
0#
b10 "
bx !
$end
#10
b0 !
b0 )
1#
#20
0#
1%
0&
#30
b10100101 !
b10100101 )
1#
#40
0#
1&
b111100 $
b111100 (
b101 "
b101 '
0%
#50
b0 !
b0 )
1#
#60
0#
1%
0&
#70
b111100 !
b111100 )
1#
#80
0#
b10 "
b10 '
0%
#90
b0 !
b0 )
1#
